merge_files/__init__.py
merge_files/__main__.py
merge_files/main.py
merge_files/utils.py
merge_files/mergers/async_.py
merge_files/mergers/base.py
merge_files/mergers/basic.py
merge_files/mergers/parallel.py
sorted_file_merger-0.1.0.dist-info/METADATA
sorted_file_merger-0.1.0.dist-info/WHEEL
sorted_file_merger-0.1.0.dist-info/entry_points.txt
sorted_file_merger-0.1.0.dist-info/top_level.txt
sorted_file_merger-0.1.0.dist-info/RECORD
