Metadata-Version: 2.1
Name: sorted-file-merger
Version: 0.1.0
Summary: A CLI tool to merge multiple sorted files into a single sorted output file.
Author: Hakan Bogan
Author-email: hb@hakanbogan.com
Classifier: Programming Language :: Python :: 3
Classifier: License :: OSI Approved :: MIT License
Classifier: Operating System :: OS Independent
Requires-Python: >=3.6
Requires-Dist: faker (==17.0.0)
Requires-Dist: coverage (==7.1.0)
